tfism/__init__.py
tfism/core.py
tfism/py.typed
tfism/version.py
tfism/experimental/__init__.py
tfism/experimental/utils.py
tfism/extensions/__init__.py
tfism/extensions/asyncio.py
tfism/extensions/diagrams.py
tfism/extensions/diagrams_base.py
tfism/extensions/diagrams_graphviz.py
tfism/extensions/diagrams_mermaid.py
tfism/extensions/diagrams_pygraphviz.py
tfism/extensions/factory.py
tfism/extensions/locking.py
tfism/extensions/markup.py
tfism/extensions/nesting.py
tfism/extensions/states.py
tfism-0.9.5.post4.data/data/tfism/py.typed
tfism-0.9.5.post4.dist-info/METADATA
tfism-0.9.5.post4.dist-info/WHEEL
tfism-0.9.5.post4.dist-info/licenses/LICENSE
tfism-0.9.5.post4.dist-info/RECORD
