Metadata-Version: 2.4
Name: tfism
Version: 0.9.5.post4
Summary: A lightweight, object-oriented Python state machine implementation with many extensions.
Project-URL: Homepage, http://github.com/pytransitions/tfism
Project-URL: Documentation, https://github.com/pytransitions/tfism
Project-URL: Repository, https://github.com/pytransitions/tfism
Project-URL: Bug Tracker, https://github.com/pytransitions/tfism/issues
Project-URL: Source Code, https://github.com/pytransitions/tfism
Project-URL: Download, https://github.com/pytransitions/tfism/archive/%s.tar.gz
Author-email: Tal Yarkoni <tyarkoni@gmail.com>
Maintainer-email: Alexander Neumann <aleneum@gmail.com>
License: MIT
License-File: LICENSE
Keywords: finite state machine,fsm,state machine,statemachine
Classifier: License :: OSI Approved :: MIT License
Classifier: Programming Language :: Python :: 3
Classifier: Programming Language :: Python :: 3.10
Classifier: Programming Language :: Python :: 3.11
Classifier: Programming Language :: Python :: 3.12
Classifier: Programming Language :: Python :: 3.13
Classifier: Programming Language :: Python :: 3.14
Requires-Python: >=3.10
Provides-Extra: all
Requires-Dist: dill; extra == 'all'
Requires-Dist: graphviz; extra == 'all'
Requires-Dist: mock; extra == 'all'
Requires-Dist: mypy; extra == 'all'
Requires-Dist: pycodestyle; extra == 'all'
Requires-Dist: pygraphviz; extra == 'all'
Requires-Dist: pytest-cov; extra == 'all'
Requires-Dist: pytest-runner; extra == 'all'
Requires-Dist: pytest-xdist; extra == 'all'
Requires-Dist: pytest>=7.0; extra == 'all'
Requires-Dist: types-mock; extra == 'all'
Provides-Extra: dev
Requires-Dist: dill; extra == 'dev'
Requires-Dist: mock; extra == 'dev'
Requires-Dist: mypy; extra == 'dev'
Requires-Dist: pycodestyle; extra == 'dev'
Requires-Dist: pytest-cov; extra == 'dev'
Requires-Dist: pytest-runner; extra == 'dev'
Requires-Dist: pytest-xdist; extra == 'dev'
Requires-Dist: pytest>=7.0; extra == 'dev'
Requires-Dist: types-mock; extra == 'dev'
Provides-Extra: diagrams
Requires-Dist: graphviz; extra == 'diagrams'
Requires-Dist: pygraphviz; extra == 'diagrams'
Provides-Extra: mypy
Requires-Dist: mypy; extra == 'mypy'
Requires-Dist: types-mock; extra == 'mypy'
Provides-Extra: test
Requires-Dist: dill; extra == 'test'
Requires-Dist: mock; extra == 'test'
Requires-Dist: pycodestyle; extra == 'test'
Requires-Dist: pytest-cov; extra == 'test'
Requires-Dist: pytest-runner; extra == 'test'
Requires-Dist: pytest-xdist; extra == 'test'
Requires-Dist: pytest>=7.0; extra == 'test'
